utsavpc/__init__.py
utsavpc-1.0.dist-info/Licence.txt
utsavpc-1.0.dist-info/METADATA
utsavpc-1.0.dist-info/WHEEL
utsavpc-1.0.dist-info/top_level.txt
utsavpc-1.0.dist-info/RECORD
